[
    {
        "productCategoryId": "hot_coffee",
        "productCategoryName": "Hot Coffee",
        "productCategoryDesc": "",
        "image": "assets/images/dummy/ic_hot_coffee.png"
    },
    {
        "productCategoryId": "iced_coffee",
        "productCategoryName": "Iced Coffee",
        "productCategoryDesc": "",
        "image": "assets/images/dummy/ic_iced_coffee.png"
    },
    {
        "productCategoryId": "pasta",
        "productCategoryName": "Pasta",
        "productCategoryDesc": "",
        "image": "assets/images/dummy/ic_pasta.png"
    },
    {
        "productCategoryId": "bread",
        "productCategoryName": "Bread",
        "productCategoryDesc": "",
        "image": "assets/images/dummy/ic_bread.png"
    }
]